{"__symbolic":"module","version":1,"metadata":{"CoachPage":{"__symbolic":"class","decorators":[{"__symbolic":"call","expression":{"__symbolic":"reference","module":"@angular/core","name":"Component"},"arguments":[{"templateUrl":"coach.html"}]}],"members":{"__ctor__":[{"__symbolic":"constructor","parameters":[{"__symbolic":"reference","module":"ionic-angular","name":"NavController"},{"__symbolic":"reference","module":"ionic-angular","name":"NavParams"},{"__symbolic":"reference","module":"../../services/request","name":"Request"}]}],"getWorkouts":[{"__symbolic":"method"}],"check":[{"__symbolic":"method"}],"uncheck":[{"__symbolic":"method"}]}}}}